{
  "sheetsById": {
    "R3F UI": {
      "staticOverrides": {
        "byObject": {
          "Editor Camera snapshot #1": {
            "transform": {
              "position": {
                "x": 10.52631578947357,
                "y": 10.526315789473593,
                "z": 6.445509469196526e-16
              },
              "target": {
                "x": 0,
                "y": 0,
                "z": 0
              }
            }
          },
          "Editor": {
            "transformControls": {
              "mode": "translate"
            }
          }
        }
      }
    },
    "Scene": {
      "staticOverrides": {
        "byObject": {}
      },
      "sequence": {
        "subUnitsPerUnit": 30,
        "length": 10,
        "type": "PositionalSequence",
        "tracksByObject": {
          "MilkBottle": {
            "trackData": {
              "Hx940CgEgV": {
                "type": "BasicKeyframedTrack",
                "__debugName": "MilkBottle:[\"position\",\"x\"]",
                "keyframes": [
                  {
                    "id": "I1pb46GFV5",
                    "position": 0,
                    "connectedRight": true,
                    "handles": [
                      0.5,
                      1,
                      0.5,
                      0
                    ],
                    "value": 0
                  },
                  {
                    "id": "VJBkuK37qT",
                    "position": 2.167,
                    "connectedRight": true,
                    "handles": [
                      0.5,
                      1,
                      0.5,
                      0
                    ],
                    "value": 0
                  },
                  {
                    "id": "3wGOB-5NWV",
                    "position": 5.033,
                    "connectedRight": true,
                    "handles": [
                      0.5,
                      1,
                      0.5,
                      0
                    ],
                    "value": 0
                  },
                  {
                    "id": "CPF_JTBD-B",
                    "position": 7.2,
                    "connectedRight": true,
                    "handles": [
                      0.5,
                      1,
                      0.5,
                      0
                    ],
                    "value": 0
                  },
                  {
                    "id": "cCtOENPTOr",
                    "position": 8.267,
                    "connectedRight": true,
                    "handles": [
                      0.5,
                      1,
                      0.5,
                      0
                    ],
                    "value": 0
                  },
                  {
                    "id": "O69RhCpdrN",
                    "position": 9.367,
                    "connectedRight": true,
                    "handles": [
                      0.5,
                      1,
                      0.5,
                      0
                    ],
                    "value": 2.0860613350878756
                  },
                  {
                    "id": "ozuhZh8fsb",
                    "position": 9.633,
                    "connectedRight": true,
                    "handles": [
                      0.5,
                      1,
                      0.5,
                      0
                    ],
                    "value": 2.0860613350878756
                  }
                ]
              },
              "vItSRgzEOy": {
                "type": "BasicKeyframedTrack",
                "__debugName": "MilkBottle:[\"position\",\"y\"]",
                "keyframes": [
                  {
                    "id": "TGDGbghAV2",
                    "position": 0,
                    "connectedRight": true,
                    "handles": [
                      0.5,
                      1,
                      0.5,
                      0
                    ],
                    "value": -2.0116832087835066
                  },
                  {
                    "id": "Fv3fSkz61M",
                    "position": 2.167,
                    "connectedRight": true,
                    "handles": [
                      0.5,
                      1,
                      0.5,
                      0
                    ],
                    "value": -2.0116832087835066
                  },
                  {
                    "id": "LwJOM4e73W",
                    "position": 5.033,
                    "connectedRight": true,
                    "handles": [
                      0.5,
                      1,
                      0.5,
                      0
                    ],
                    "value": -0.43181471570242813
                  },
                  {
                    "id": "Ojd2uMNWKs",
                    "position": 7.2,
                    "connectedRight": true,
                    "handles": [
                      0.5,
                      1,
                      0.5,
                      0
                    ],
                    "value": 0.4014544961840091
                  },
                  {
                    "id": "hLDmZGc4AY",
                    "position": 8.267,
                    "connectedRight": true,
                    "handles": [
                      0.5,
                      1,
                      0.5,
                      0
                    ],
                    "value": 0.4014544961840091
                  },
                  {
                    "id": "uRHIIaM8xx",
                    "position": 9.367,
                    "connectedRight": true,
                    "handles": [
                      0.5,
                      1,
                      0.5,
                      0
                    ],
                    "value": 0.4014544961840091
                  },
                  {
                    "id": "k2Mzw0zjT9",
                    "position": 9.633,
                    "connectedRight": true,
                    "handles": [
                      0.5,
                      1,
                      0.5,
                      0
                    ],
                    "value": 0.4014544961840091
                  }
                ]
              },
              "aSJBejjEVr": {
                "type": "BasicKeyframedTrack",
                "__debugName": "MilkBottle:[\"position\",\"z\"]",
                "keyframes": [
                  {
                    "id": "joX2I2ChZ8",
                    "position": 0,
                    "connectedRight": true,
                    "handles": [
                      0.5,
                      1,
                      0.5,
                      0
                    ],
                    "value": -1
                  },
                  {
                    "id": "mx88XHWSba",
                    "position": 2.167,
                    "connectedRight": true,
                    "handles": [
                      0.5,
                      1,
                      0.5,
                      0
                    ],
                    "value": 13.774393715304099
                  },
                  {
                    "id": "I062Mbfqvo",
                    "position": 5.033,
                    "connectedRight": true,
                    "handles": [
                      0.5,
                      1,
                      0.5,
                      0
                    ],
                    "value": 13.774393715304099
                  },
                  {
                    "id": "_2nby1Niql",
                    "position": 7.2,
                    "connectedRight": true,
                    "handles": [
                      0.5,
                      1,
                      0.5,
                      0
                    ],
                    "value": 13.774393715304099
                  },
                  {
                    "id": "h_6ftzktjZ",
                    "position": 8.267,
                    "connectedRight": true,
                    "handles": [
                      0.5,
                      1,
                      0.5,
                      0
                    ],
                    "value": 13.774393715304099
                  },
                  {
                    "id": "DdPQPrPrPz",
                    "position": 9.367,
                    "connectedRight": true,
                    "handles": [
                      0.5,
                      1,
                      0.5,
                      0
                    ],
                    "value": 13.774393715304099
                  },
                  {
                    "id": "2qO_D26xOX",
                    "position": 9.633,
                    "connectedRight": true,
                    "handles": [
                      0.5,
                      1,
                      0.5,
                      0
                    ],
                    "value": 13.774393715304099
                  }
                ]
              },
              "zhD92Zn_b-": {
                "type": "BasicKeyframedTrack",
                "__debugName": "MilkBottle:[\"rotation\",\"x\"]",
                "keyframes": [
                  {
                    "id": "Gfwr2ErTJ_",
                    "position": 0,
                    "connectedRight": true,
                    "handles": [
                      0.5,
                      1,
                      0.5,
                      0
                    ],
                    "value": 0
                  },
                  {
                    "id": "FaOE0Bkm4h",
                    "position": 2.167,
                    "connectedRight": true,
                    "handles": [
                      0.5,
                      1,
                      0.5,
                      0
                    ],
                    "value": 0
                  },
                  {
                    "id": "6djcPmVK3K",
                    "position": 5.033,
                    "connectedRight": true,
                    "handles": [
                      0.5,
                      1,
                      0.5,
                      0
                    ],
                    "value": 0
                  },
                  {
                    "id": "J3uxSvDRWp",
                    "position": 7.2,
                    "connectedRight": true,
                    "handles": [
                      0.5,
                      1,
                      0.5,
                      0
                    ],
                    "value": 0
                  },
                  {
                    "id": "IuKufcU2nR",
                    "position": 8.267,
                    "connectedRight": true,
                    "handles": [
                      0.5,
                      1,
                      0.5,
                      0
                    ],
                    "value": 0
                  },
                  {
                    "id": "Y9j8K2uZQr",
                    "position": 9.367,
                    "connectedRight": true,
                    "handles": [
                      0.5,
                      1,
                      0.5,
                      0
                    ],
                    "value": 0
                  },
                  {
                    "id": "_Sn94IA8iK",
                    "position": 9.633,
                    "connectedRight": true,
                    "handles": [
                      0.5,
                      1,
                      0.5,
                      0
                    ],
                    "value": 0
                  }
                ]
              },
              "IpcwQ844-n": {
                "type": "BasicKeyframedTrack",
                "__debugName": "MilkBottle:[\"rotation\",\"y\"]",
                "keyframes": [
                  {
                    "id": "kCOjHkut06",
                    "position": 0,
                    "connectedRight": true,
                    "handles": [
                      0.5,
                      1,
                      0.5,
                      0
                    ],
                    "value": 0
                  },
                  {
                    "id": "gqELud5WfM",
                    "position": 2.167,
                    "connectedRight": true,
                    "handles": [
                      0.5,
                      1,
                      0.5,
                      0
                    ],
                    "value": 0
                  },
                  {
                    "id": "UABFtpxned",
                    "position": 5.033,
                    "connectedRight": true,
                    "handles": [
                      0.5,
                      1,
                      0.5,
                      0
                    ],
                    "value": 0
                  },
                  {
                    "id": "8bFV0vooLg",
                    "position": 7.2,
                    "connectedRight": true,
                    "handles": [
                      0.5,
                      1,
                      0.5,
                      0
                    ],
                    "value": 0
                  },
                  {
                    "id": "VLX4pv4K9R",
                    "position": 8.267,
                    "connectedRight": true,
                    "handles": [
                      0.5,
                      1,
                      0.5,
                      0
                    ],
                    "value": 0
                  },
                  {
                    "id": "wWBFTMoF9u",
                    "position": 9.367,
                    "connectedRight": true,
                    "handles": [
                      0.5,
                      1,
                      0.5,
                      0
                    ],
                    "value": 0
                  },
                  {
                    "id": "UDG8xsBtWV",
                    "position": 9.633,
                    "connectedRight": true,
                    "handles": [
                      0.5,
                      1,
                      0.5,
                      0
                    ],
                    "value": 0
                  }
                ]
              },
              "1rJkRg17Ly": {
                "type": "BasicKeyframedTrack",
                "__debugName": "MilkBottle:[\"rotation\",\"z\"]",
                "keyframes": [
                  {
                    "id": "e7ntrWiz8O",
                    "position": 0,
                    "connectedRight": true,
                    "handles": [
                      0.5,
                      1,
                      0.5,
                      0
                    ],
                    "value": 0
                  },
                  {
                    "id": "1T3uL0TsqA",
                    "position": 2.167,
                    "connectedRight": true,
                    "handles": [
                      0.5,
                      1,
                      0.5,
                      0
                    ],
                    "value": 0
                  },
                  {
                    "id": "CrexIcoKmF",
                    "position": 5.033,
                    "connectedRight": true,
                    "handles": [
                      0.5,
                      1,
                      0.5,
                      0
                    ],
                    "value": -1.250789435269695e-16
                  },
                  {
                    "id": "1AOJcLdkxK",
                    "position": 7.2,
                    "connectedRight": true,
                    "handles": [
                      0.5,
                      1,
                      0.5,
                      0
                    ],
                    "value": 1.6046994073523646
                  },
                  {
                    "id": "h0jwGSlBn0",
                    "position": 8.267,
                    "connectedRight": true,
                    "handles": [
                      0.5,
                      1,
                      0.5,
                      0
                    ],
                    "value": 1.6046994073523646
                  },
                  {
                    "id": "sMMkj7ZJue",
                    "position": 9.367,
                    "connectedRight": true,
                    "handles": [
                      0.5,
                      1,
                      0.5,
                      0
                    ],
                    "value": 1.6046994073523646
                  },
                  {
                    "id": "daD1bVmQ5C",
                    "position": 9.633,
                    "connectedRight": true,
                    "handles": [
                      0.5,
                      1,
                      0.5,
                      0
                    ],
                    "value": 1.394570821570916
                  }
                ]
              },
              "q_V_PimKFx": {
                "type": "BasicKeyframedTrack",
                "__debugName": "MilkBottle:[\"scale\",\"x\"]",
                "keyframes": [
                  {
                    "id": "_QenaKbCcH",
                    "position": 0,
                    "connectedRight": true,
                    "handles": [
                      0.5,
                      1,
                      0.5,
                      0
                    ],
                    "value": 1
                  },
                  {
                    "id": "H5C_RB7jqW",
                    "position": 2.167,
                    "connectedRight": true,
                    "handles": [
                      0.5,
                      1,
                      0.5,
                      0
                    ],
                    "value": 1
                  },
                  {
                    "id": "uGR540rK7a",
                    "position": 5.033,
                    "connectedRight": true,
                    "handles": [
                      0.5,
                      1,
                      0.5,
                      0
                    ],
                    "value": 1
                  },
                  {
                    "id": "3adxgXgzdC",
                    "position": 7.2,
                    "connectedRight": true,
                    "handles": [
                      0.5,
                      1,
                      0.5,
                      0
                    ],
                    "value": 1
                  },
                  {
                    "id": "5844N8zGNT",
                    "position": 8.267,
                    "connectedRight": true,
                    "handles": [
                      0.5,
                      1,
                      0.5,
                      0
                    ],
                    "value": 1
                  },
                  {
                    "id": "lTjbjHiFcp",
                    "position": 9.367,
                    "connectedRight": true,
                    "handles": [
                      0.5,
                      1,
                      0.5,
                      0
                    ],
                    "value": 1
                  },
                  {
                    "id": "fYRqHlhIFI",
                    "position": 9.633,
                    "connectedRight": true,
                    "handles": [
                      0.5,
                      1,
                      0.5,
                      0
                    ],
                    "value": 1
                  }
                ]
              },
              "ctQzHBZ97W": {
                "type": "BasicKeyframedTrack",
                "__debugName": "MilkBottle:[\"scale\",\"y\"]",
                "keyframes": [
                  {
                    "id": "0mKPjkEq_U",
                    "position": 0,
                    "connectedRight": true,
                    "handles": [
                      0.5,
                      1,
                      0.5,
                      0
                    ],
                    "value": 1
                  },
                  {
                    "id": "-Qdt77MPEl",
                    "position": 2.167,
                    "connectedRight": true,
                    "handles": [
                      0.5,
                      1,
                      0.5,
                      0
                    ],
                    "value": 1
                  },
                  {
                    "id": "nInUCm9b70",
                    "position": 5.033,
                    "connectedRight": true,
                    "handles": [
                      0.5,
                      1,
                      0.5,
                      0
                    ],
                    "value": 1
                  },
                  {
                    "id": "o0HhEzKhKS",
                    "position": 7.2,
                    "connectedRight": true,
                    "handles": [
                      0.5,
                      1,
                      0.5,
                      0
                    ],
                    "value": 1
                  },
                  {
                    "id": "rT2Vx1MwaD",
                    "position": 8.267,
                    "connectedRight": true,
                    "handles": [
                      0.5,
                      1,
                      0.5,
                      0
                    ],
                    "value": 1
                  },
                  {
                    "id": "Z0FAglIzik",
                    "position": 9.367,
                    "connectedRight": true,
                    "handles": [
                      0.5,
                      1,
                      0.5,
                      0
                    ],
                    "value": 1
                  },
                  {
                    "id": "Hx6AoAEE8Q",
                    "position": 9.633,
                    "connectedRight": true,
                    "handles": [
                      0.5,
                      1,
                      0.5,
                      0
                    ],
                    "value": 1
                  }
                ]
              },
              "FON0yjwWPv": {
                "type": "BasicKeyframedTrack",
                "__debugName": "MilkBottle:[\"scale\",\"z\"]",
                "keyframes": [
                  {
                    "id": "E311KG7rce",
                    "position": 0,
                    "connectedRight": true,
                    "handles": [
                      0.5,
                      1,
                      0.5,
                      0
                    ],
                    "value": 1
                  },
                  {
                    "id": "gkueZWHgiI",
                    "position": 2.167,
                    "connectedRight": true,
                    "handles": [
                      0.5,
                      1,
                      0.5,
                      0
                    ],
                    "value": 1
                  },
                  {
                    "id": "wXqsVhTnY_",
                    "position": 5.033,
                    "connectedRight": true,
                    "handles": [
                      0.5,
                      1,
                      0.5,
                      0
                    ],
                    "value": 1
                  },
                  {
                    "id": "Kyr1XuZMBK",
                    "position": 7.2,
                    "connectedRight": true,
                    "handles": [
                      0.5,
                      1,
                      0.5,
                      0
                    ],
                    "value": 1
                  },
                  {
                    "id": "vcWDpjLwcf",
                    "position": 8.267,
                    "connectedRight": true,
                    "handles": [
                      0.5,
                      1,
                      0.5,
                      0
                    ],
                    "value": 1
                  },
                  {
                    "id": "ox-cS9KbYb",
                    "position": 9.367,
                    "connectedRight": true,
                    "handles": [
                      0.5,
                      1,
                      0.5,
                      0
                    ],
                    "value": 1
                  },
                  {
                    "id": "AkSL3_D1eP",
                    "position": 9.633,
                    "connectedRight": true,
                    "handles": [
                      0.5,
                      1,
                      0.5,
                      0
                    ],
                    "value": 1
                  }
                ]
              }
            },
            "trackIdByPropPath": {
              "[\"position\",\"x\"]": "Hx940CgEgV",
              "[\"position\",\"y\"]": "vItSRgzEOy",
              "[\"position\",\"z\"]": "aSJBejjEVr",
              "[\"rotation\",\"x\"]": "zhD92Zn_b-",
              "[\"rotation\",\"y\"]": "IpcwQ844-n",
              "[\"rotation\",\"z\"]": "1rJkRg17Ly",
              "[\"scale\",\"x\"]": "q_V_PimKFx",
              "[\"scale\",\"y\"]": "ctQzHBZ97W",
              "[\"scale\",\"z\"]": "FON0yjwWPv"
            }
          }
        }
      }
    }
  },
  "definitionVersion": "0.4.0",
  "revisionHistory": [
    "VhCXIoMofUeV62ac",
    "zOeq9Xg42HkBSypd",
    "86Tlt73OdMQ_ipLX"
  ]
}